Jstnum/__init__.py
Jstnum/module.py
Jstnum-0.2.dist-info/LICENSE
Jstnum-0.2.dist-info/METADATA
Jstnum-0.2.dist-info/WHEEL
Jstnum-0.2.dist-info/top_level.txt
Jstnum-0.2.dist-info/RECORD
