Metadata-Version: 2.1
Name: Jstnum
Version: 0.2
Summary: JynPopMod Python Module
Home-page: https://github.com/Jynoqtra/JynPopMod
Author: Jynoqtra
Author-email: Jynoqtra@gmail.com
Classifier: Programming Language :: Python :: 3
Classifier: License :: OSI Approved :: MIT License
Classifier: Intended Audience :: Developers
License-File: LICENSE
Requires-Dist: better-profanity
Requires-Dist: textblob
Requires-Dist: scikit-learn
Requires-Dist: pyperclip
